[{"archived":false,"brand":"cojp","byline":"Hannah Levitt","credits":[{"editorialBoard":false,"roles":["by","reporter"],"name":"Hannah Levitt","attributionPreferences":{"fullNamePreference":"Hannah Levitt","__typename":"AttributionDetails"},"__typename":"Person","site":"cojp","photoDisplayed":false,"thumbnail":null}],"eyebrow":{"url":"","text":"Cojp","bybrowEligible":false},"headline":"ダイモン氏、クレジット市場低迷のリスク警告－深刻化の可能性指摘","id":"TE7N1GT9NJLT00","image":{"alt":"Norges Bank Investment Management Annual Investment Conference ","baseUrl":"https://assets.bwbx.io/images/users/iqjWHBFdfxIU/imOdflMU31L8/v1/-1x-1.webp","caption":"","credit":"Carina Johansen/Bloomberg","origWidth":2000,"origHeight":1333,"themes":[],"type":"image"},"lede":{"alt":"JPモルガン・チェースのジェイミー・ダイモン最高経営責任者（4月28日）","baseUrl":"https://assets.bwbx.io/images/users/iqjWHBFdfxIU/imOdflMU31L8/v1/-1x-1.webp","caption":"<p>JPモルガン・チェースのジェイミー・ダイモン最高経営責任者（4月28日）</p>","credit":"Photographer: Carina Johansen/Bloomberg","origWidth":2000,"origHeight":1333,"themes":[],"type":"image"},"locale":"ja","media":{"defaultImage":{"alt":"Norges Bank Investment Management Annual Investment Conference ","baseUrl":"https://assets.bwbx.io/images/users/iqjWHBFdfxIU/imOdflMU31L8/v1/-1x-1.webp","caption":"","credit":"Carina Johansen/Bloomberg","origWidth":2000,"origHeight":1333,"placement":"","themes":[],"type":"image"}},"meta":{"terminalBlogId":null,"__typename":"Meta"},"premium":false,"publishedAt":"2026-04-28T16:16:32.062Z","slug":"2026-04-28/TE7N1GT9NJLT00","summary":"","trackingType":"Story","type":"article","updatedAt":"2026-04-28T16:16:32.062Z","url":"/jp/news/articles/2026-04-28/TE7N1GT9NJLT00","__modelType":"Story"},{"archived":false,"brand":"cojp","byline":"Mia Gindis、Paul Burkhardt","credits":[{"editorialBoard":false,"roles":["by","reporter"],"name":"Mia Gindis","attributionPreferences":{"fullNamePreference":"Mia Gindis","__typename":"AttributionDetails"},"__typename":"Person","site":"cojp","photoDisplayed":false,"thumbnail":null},{"editorialBoard":false,"roles":["by","reporter"],"name":"Paul Burkhardt","attributionPreferences":{"fullNamePreference":"Paul Burkhardt","__typename":"AttributionDetails"},"__typename":"Person","site":"cojp","photoDisplayed":false,"thumbnail":null}],"eyebrow":{"url":"","text":"Cojp","bybrowEligible":false},"headline":"原油上昇、イラン提案への米対応待ち－UAEのOPEC脱退で一時上げ縮小","id":"TE7HE6KJH6V5","image":{"alt":"An oil field","baseUrl":"https://assets.bwbx.io/images/users/iqjWHBFdfxIU/iOPF1rcoSAeI/v0/-1x-1.webp","caption":"","credit":"Brandon Bell/Getty Images","origWidth":2200,"origHeight":1467,"themes":[],"type":"image"},"lede":{"autoplay":true,"bmmrId":"9aa33aa1-fea3-4902-8a6c-e3fd655c40a9","prerollAdUnit":"","url":"","thumbnail":{"alt":"","baseUrl":"https://assets.bwbx.io/images/users/iqjWHBFdfxIU/i6PL8IVnXHNM/v3/-1x-1.webp","caption":"","credit":"","origWidth":1920,"origHeight":1080,"themes":[],"type":"image"},"title":"Trump Discusses Latest Iran Proposal With Aides","duration":202100,"type":"Video","keywords":[],"showName":"","aspectRatio":"16:9"},"locale":"ja","media":{"defaultImage":{"alt":"An oil field","baseUrl":"https://assets.bwbx.io/images/users/iqjWHBFdfxIU/iOPF1rcoSAeI/v0/-1x-1.webp","caption":"","credit":"Brandon Bell/Getty Images","origWidth":2200,"origHeight":1467,"placement":"","themes":[],"type":"image"}},"meta":{"terminalBlogId":null,"__typename":"Meta"},"premium":false,"publishedAt":"2026-04-28T15:25:18.412Z","slug":"2026-04-28/TE7HE6KJH6V5","summary":"","trackingType":"Story","type":"article","updatedAt":"2026-04-28T15:25:18.412Z","url":"/jp/news/articles/2026-04-28/TE7HE6KJH6V5","__modelType":"Story"},{"archived":false,"brand":"cojp","byline":"David Welch","credits":[{"editorialBoard":false,"roles":["by","reporter"],"name":"David Welch","attributionPreferences":{"fullNamePreference":"David Welch","__typename":"AttributionDetails"},"__typename":"Person","site":"cojp","photoDisplayed":false,"thumbnail":null}],"eyebrow":{"url":"","text":"Cojp","bybrowEligible":false},"headline":"GMが警告、インフレは「広範囲」で影響－利益見通しを押し下げ","id":"TE7J8JKK3NYP00","image":{"alt":"General Motors Vehicles Ahead Of Earnings Figures","baseUrl":"https://assets.bwbx.io/images/users/iqjWHBFdfxIU/ixJFJJHq2_Aw/v0/-1x-1.webp","caption":"","credit":"Kyle Grillot/Bloomberg","origWidth":2000,"origHeight":1343,"themes":[],"type":"image"},"locale":"ja","media":{"defaultImage":{"alt":"General Motors Vehicles Ahead Of Earnings Figures","baseUrl":"https://assets.bwbx.io/images/users/iqjWHBFdfxIU/ixJFJJHq2_Aw/v0/-1x-1.webp","caption":"","credit":"Kyle Grillot/Bloomberg","origWidth":2000,"origHeight":1343,"placement":"","themes":[],"type":"image"}},"meta":{"terminalBlogId":null,"__typename":"Meta"},"premium":false,"publishedAt":"2026-04-28T15:24:58.016Z","slug":"2026-04-28/TE7J8JKK3NYP00","summary":"","trackingType":"Story","type":"article","updatedAt":"2026-04-28T15:24:58.016Z","url":"/jp/news/articles/2026-04-28/TE7J8JKK3NYP00","__modelType":"Story"},{"archived":false,"brand":"cojp","byline":"Bloomberg News","credits":[],"eyebrow":{"url":"","text":"Cojp","bybrowEligible":false},"headline":"マナス買収阻止の余波広がる－中国テック大手、米中で事業分割厳格化","id":"TE7AOUKK3NYE00","image":{"alt":"Shanda Group Chairman And Billionaire Chen Tiangqiao and Vice Chairman Chrissy Luo Interview","baseUrl":"https://assets.bwbx.io/images/users/iqjWHBFdfxIU/ibFcXqtB4uqQ/v0/-1x-1.webp","caption":"","credit":"Sanjit Das/Bloomberg","origWidth":2000,"origHeight":1334,"themes":[],"type":"image"},"lede":{"alt":"ミロマインド創業者の陳天橋氏（米カリフォルニア州の自宅で）","baseUrl":"https://assets.bwbx.io/images/users/iqjWHBFdfxIU/iZKM5rAKH18o/v2/-1x-1.webp","caption":"<p>ミロマインド創業者の陳天橋氏（米カリフォルニア州の自宅で）</p>","credit":"Photographer: Poppy Lynch/Bloomberg","origWidth":2000,"origHeight":1334,"themes":[],"type":"image"},"locale":"ja","media":{"defaultImage":{"alt":"Shanda Group Chairman And Billionaire Chen Tiangqiao and Vice Chairman Chrissy Luo Interview","baseUrl":"https://assets.bwbx.io/images/users/iqjWHBFdfxIU/ibFcXqtB4uqQ/v0/-1x-1.webp","caption":"","credit":"Sanjit Das/Bloomberg","origWidth":2000,"origHeight":1334,"placement":"","themes":[],"type":"image"}},"meta":{"terminalBlogId":null,"__typename":"Meta"},"premium":false,"publishedAt":"2026-04-28T15:14:26.860Z","slug":"2026-04-28/TE7AOUKK3NYE00","summary":"","trackingType":"Story","type":"article","updatedAt":"2026-04-28T15:16:30.670Z","url":"/jp/news/articles/2026-04-28/TE7AOUKK3NYE00","__modelType":"Story"},{"archived":false,"brand":"cojp","byline":"Natasha Mascarenhas","credits":[{"editorialBoard":false,"roles":["by","reporter"],"name":"Natasha Mascarenhas","attributionPreferences":{"fullNamePreference":"Natasha Mascarenhas","__typename":"AttributionDetails"},"__typename":"Person","site":"cojp","photoDisplayed":false,"thumbnail":null}],"eyebrow":{"url":"","text":"Cojp","bybrowEligible":false},"headline":"ベンチャーキャピタル、AI人材を社内に取り込み－投資先の実装支援","id":"TE7DVCKIJH9H00","image":{"alt":"A Cloudflare Inc. Location As Company Files IPO","baseUrl":"https://assets.bwbx.io/images/users/iqjWHBFdfxIU/i1leTuIRlzUA/v0/-1x-1.webp","caption":"","credit":"Michael Short/Bloomberg","origWidth":2000,"origHeight":1335,"themes":[],"type":"image"},"locale":"ja","media":{"defaultImage":{"alt":"A Cloudflare Inc. Location As Company Files IPO","baseUrl":"https://assets.bwbx.io/images/users/iqjWHBFdfxIU/i1leTuIRlzUA/v0/-1x-1.webp","caption":"","credit":"Michael Short/Bloomberg","origWidth":2000,"origHeight":1335,"placement":"","themes":[],"type":"image"}},"meta":{"terminalBlogId":null,"__typename":"Meta"},"premium":false,"publishedAt":"2026-04-28T15:13:45.182Z","slug":"2026-04-28/TE7DVCKIJH9H00","summary":"","trackingType":"Story","type":"article","updatedAt":"2026-04-28T15:13:45.182Z","url":"/jp/news/articles/2026-04-28/TE7DVCKIJH9H00","__modelType":"Story"}]